setup.py
d3_chart_builder/__init__.py
d3_chart_builder/d3_property_generator.py
d3_chart_builder/personal_statistics.py
d3_chart_builder/test_sdf.py
d3_chart_builder/top_k_ranking.py
d3_chart_builder.egg-info/PKG-INFO
d3_chart_builder.egg-info/SOURCES.txt
d3_chart_builder.egg-info/dependency_links.txt
d3_chart_builder.egg-info/not-zip-safe
d3_chart_builder.egg-info/top_level.txt