Metadata-Version: 1.0
Name: d3-chart-builder
Version: 0.0.5
Summary: D3 chart builder for python
Home-page: http://github.com/abc123634/d3_chart_builder
Author: Lee Meng
Author-email: leemeng@marketenterprise.co.jp
License: MIT
Platform: UNKNOWN
